llama_index/tools/brightdata/__init__.py
llama_index/tools/brightdata/base.py
llama_index_tools_brightdata-0.2.1.dist-info/METADATA
llama_index_tools_brightdata-0.2.1.dist-info/WHEEL
llama_index_tools_brightdata-0.2.1.dist-info/licenses/LICENSE
llama_index_tools_brightdata-0.2.1.dist-info/RECORD
