Metadata-Version: 2.4
Name: llama-index-tools-brightdata
Version: 0.2.1
Summary: llama-index tools Bright Data integration
Author-email: Bright Data <you@example.com>
Maintainer: brightdata
License-Expression: MIT
License-File: LICENSE
Requires-Python: <4.0,>=3.9
Requires-Dist: llama-index-core<0.15,>=0.13.0
